logica/__main__.py
logica/colab_logica.py
logica/logica.py
logica/run_all_tests.py
logica/common/callclingo.py
logica/common/clingo_logica.py
logica/common/color.py
logica/common/concertina_lib.py
logica/common/duckdb_logica.py
logica/common/graph.py
logica/common/graph_art.py
logica/common/image.py
logica/common/intelligence.py
logica/common/logica_lib.py
logica/common/logica_test.py
logica/common/platonic.py
logica/common/platonic_test.py
logica/common/psql_logica.py
logica/common/sqlite3_logica.py
logica/common/data/processed_functions.py
logica/compiler/dialects.py
logica/compiler/expr_translate.py
logica/compiler/functors.py
logica/compiler/rule_translate.py
logica/compiler/universe.py
logica/compiler/dialect_libraries/bq_library.py
logica/compiler/dialect_libraries/databricks_library.py
logica/compiler/dialect_libraries/duckdb_library.py
logica/compiler/dialect_libraries/presto_library.py
logica/compiler/dialect_libraries/psql_library.py
logica/compiler/dialect_libraries/recursion_library.py
logica/compiler/dialect_libraries/sqlite_library.py
logica/compiler/dialect_libraries/trino_library.py
logica/examples/more/call_postgres.py
logica/examples/more/call_sqlite.py
logica/integration_tests/run_tests.py
logica/integration_tests/import_tests/run_tests.py
logica/parser_py/parse.py
logica/tools/avatar.py
logica/tools/proposition_repl.py
logica/tools/run_in_terminal.py
logica/type_inference/bad_schema_exception.py
logica/type_inference/bq_type_parser.py
logica/type_inference/bq_type_retrieval_service.py
logica/type_inference/bq_type_retriever.py
logica/type_inference/built_in_functions_types.py
logica/type_inference/intersection.py
logica/type_inference/psql_type_parser.py
logica/type_inference/psql_type_retrieval_service.py
logica/type_inference/psql_type_retriever.py
logica/type_inference/type_inference_exception.py
logica/type_inference/type_inference_service.py
logica/type_inference/type_retrieval_exception.py
logica-1.3.1415926535897.dist-info/METADATA
logica-1.3.1415926535897.dist-info/WHEEL
logica-1.3.1415926535897.dist-info/entry_points.txt
logica-1.3.1415926535897.dist-info/top_level.txt
logica-1.3.1415926535897.dist-info/RECORD
