Metadata-Version: 2.4
Name: logica
Version: 1.3.1415926535897
Summary: Logica language.
Home-page: https://github.com/evgskv/logica
Author: Evgeny Skvortsov
Author-email: logica@evgeny.ninja
Classifier: Topic :: Database
Classifier: License :: OSI Approved :: Apache Software License
Requires-Python: >=3.0
Dynamic: author
Dynamic: author-email
Dynamic: classifier
Dynamic: description
Dynamic: description-content-type
Dynamic: home-page
Dynamic: requires-python
Dynamic: summary
